simple_socialauth/__init__.py
simple_socialauth/admin.py
simple_socialauth/apps.py
simple_socialauth/backends.py
simple_socialauth/forms.py
simple_socialauth/models.py
simple_socialauth/settings.py
simple_socialauth/signals.py
simple_socialauth/urls.py
simple_socialauth/views.py
simple_socialauth/migrations/0001_initial.py
simple_socialauth/migrations/__init__.py
simple_socialauth/providers/__init__.py
simple_socialauth/providers/angellist.py
simple_socialauth/providers/base.py
simple_socialauth/providers/facebook.py
simple_socialauth/providers/github.py
simple_socialauth/providers/google.py
simple_socialauth/providers/linkedin.py
simple_socialauth/providers/pinterest.py
simple_socialauth/providers/twitter.py
django_simple_socialauth-2.1.0.dist-info/LICENSE
django_simple_socialauth-2.1.0.dist-info/METADATA
django_simple_socialauth-2.1.0.dist-info/WHEEL
django_simple_socialauth-2.1.0.dist-info/top_level.txt
django_simple_socialauth-2.1.0.dist-info/RECORD
