Metadata-Version: 2.1
Name: django-simple-socialauth
Version: 2.1.0
Summary: Django social account authentication app based on requests-oauthlib.
Home-page: https://github.com/jaddison/django-simple-socialauth
Author: jaddison
Author-email: addi00+github.com@gmail.com
License: MIT
Keywords: django social authentication oauth register login auth
Classifier: Development Status :: 4 - Beta
Classifier: Topic :: Internet :: WWW/HTTP
Classifier: Environment :: Web Environment
Classifier: Intended Audience :: Developers
Classifier: Intended Audience :: Information Technology
Classifier: License :: OSI Approved :: MIT License
Classifier: Programming Language :: Python :: 2
Classifier: Programming Language :: Python :: 2.6
Classifier: Programming Language :: Python :: 2.7
Classifier: Programming Language :: Python :: 3
Classifier: Programming Language :: Python :: 3.3
Classifier: Programming Language :: Python :: 3.4
Classifier: Programming Language :: Python :: 3.5
Classifier: Programming Language :: Python :: 3.6
License-File: LICENSE
Requires-Dist: requests-oauthlib
